tato/__about__.py
tato/__init__.py
tato/_debug.py
tato/_graph.py
tato/_node.py
tato/_node_type.py
tato/_section.py
tato/_skipcompare.py
tato/cli.py
tato/tato.py
tato/index/__init__.py
tato/index/_collector.py
tato/index/_controller.py
tato/index/_db.py
tato/index/_definition.py
tato/index/_types.py
tato/index/db-schema.sql
tato/index/index.py
tato/index/__tests__/test_db.py
tato/index/__tests__/test_index.py
tato/index/__tests__/data/definition/test1/__init__.py
tato/index/__tests__/data/definition/test1/a.py
tato/index/__tests__/data/definition/test2/__init__.py
tato/index/__tests__/data/definition/test2/a.py
tato/index/__tests__/data/definition/test2/b.py
tato/index/__tests__/data/index/test1/__init__.py
tato/index/__tests__/data/index/test1/a.py
tato/index/__tests__/data/index/test1/b.py
tato/index/__tests__/data/index/test1/c.py
tato/lib/__init__.py
tato/lib/uuid.py
tato-0.2.3.dist-info/METADATA
tato-0.2.3.dist-info/WHEEL
tato-0.2.3.dist-info/entry_points.txt
tato-0.2.3.dist-info/licenses/LICENSE.txt
tato-0.2.3.dist-info/RECORD
