Metadata-Version: 2.3
Name: tato
Version: 0.2.3
Summary: Python file layout formatter.
Project-URL: Documentation, https://github.com/vivster7/tato#readme
Project-URL: Issues, https://github.com/vivster7/tato/issues
Project-URL: Source, https://github.com/vivster7/tato
Author-email: Vivek Dasari <vivster7@gmail.com>
License-Expression: MIT
License-File: LICENSE.txt
Keywords: autoformat,format,layout,sections
Classifier: Development Status :: 4 - Beta
Classifier: Programming Language :: Python
Classifier: Programming Language :: Python :: 3.8
Classifier: Programming Language :: Python :: 3.9
Classifier: Programming Language :: Python :: 3.10
Classifier: Programming Language :: Python :: 3.11
Classifier: Programming Language :: Python :: 3.12
Classifier: Programming Language :: Python :: Implementation :: CPython
Classifier: Programming Language :: Python :: Implementation :: PyPy
Requires-Python: >=3.8
Requires-Dist: libcst>=1.0.0
